psistat.py
psistat-1.0.0.dist-info/entry_points.txt
psistat-1.0.0.dist-info/licenses/LICENSE
psistat-1.0.0.dist-info/WHEEL
psistat-1.0.0.dist-info/METADATA
psistat-1.0.0.dist-info/RECORD
