Metadata-Version: 2.4
Name: psistat
Version: 1.0.0
Summary: psistat - A simple command-line system status tool.
Keywords: system,status,cli
Author-email: Joe Defen <joedef@duck.com>
Requires-Python: >=3.8
Classifier: Development Status :: 3 - Alpha
Classifier: Programming Language :: Python :: 3
Classifier: Programming Language :: Python :: 3.8
Classifier: License :: OSI Approved :: MIT License
Classifier: Environment :: Console
Classifier: Topic :: System :: Monitoring
License-File: LICENSE
Requires-Dist: console-window >= 1.0.0
